DeepLearningPy/__init__.py
DeepLearningPy/test.py
DeepLearningPy-0.0.1.dist-info/LICENSE
DeepLearningPy-0.0.1.dist-info/METADATA
DeepLearningPy-0.0.1.dist-info/WHEEL
DeepLearningPy-0.0.1.dist-info/top_level.txt
DeepLearningPy-0.0.1.dist-info/RECORD
